graphpype/__init__.py
graphpype/labeled_mask.py
graphpype/utils.py
graphpype/utils_cor.py
graphpype/utils_dtype_coord.py
graphpype/utils_img.py
graphpype/utils_mod.py
graphpype/utils_net.py
graphpype/utils_plot.py
graphpype/utils_stats.py
graphpype/utils_tests.py
graphpype/utils_visbrain.py
graphpype/gather/__init__.py
graphpype/gather/gather_cormats.py
graphpype/gather/gather_permuts.py
graphpype/interfaces/__init__.py
graphpype/interfaces/bct/__init__.py
graphpype/interfaces/bct/bct.py
graphpype/interfaces/radatools/__init__.py
graphpype/interfaces/radatools/rada.py
graphpype/nodes/__init__.py
graphpype/nodes/coclass.py
graphpype/nodes/correl_mat.py
graphpype/nodes/graph_stats.py
graphpype/nodes/modularity.py
graphpype/pipelines/__init__.py
graphpype/pipelines/conmat_to_graph.py
graphpype/pipelines/intmat_to_graph.py
graphpype/pipelines/nii_to_conmat.py
graphpype-0.0.9.dist-info/LICENSE
graphpype-0.0.9.dist-info/METADATA
graphpype-0.0.9.dist-info/WHEEL
graphpype-0.0.9.dist-info/top_level.txt
graphpype-0.0.9.dist-info/RECORD
