Metadata-Version: 2.1
Name: graphpype
Version: 0.0.9
Summary: Graph analysis for neuropycon (using nipype, and ephypype); based on previous packages dmgraphanalysis and then dmgraphanalysis_nodes and graphpype
Home-page: UNKNOWN
Author: David Meunier
Author-email: UNKNOWN
License: UNKNOWN
Platform: UNKNOWN
Requires-Dist: numpy (>=1.3.0)
Requires-Dist: statsmodels
Requires-Dist: patsy (==0.5.1)
Requires-Dist: nipype
Requires-Dist: configparser
Requires-Dist: pandas (==0.23.4)
Requires-Dist: xlwt
Requires-Dist: networkx (==1.9)
Requires-Dist: matplotlib (==2.2.3)
Requires-Dist: bctpy
Requires-Dist: traits (==5.2.0)
